[
  {
    "id":"royal-net","level":"easy","title":"Royal net","source":"Curated mating pattern","fen":"6k1/5Q2/6K1/8/8/8/8/8 w - - 0 1","solutions":[["f7e8"],["f7g7"]],"note":"Two queen moves finish the same net. Any checkmate is a correct answer."
  },
  {
    "id":"corner-box","level":"easy","title":"Corner box","source":"Curated mating pattern","fen":"k7/8/1QK5/8/8/8/8/8 w - - 0 1","solutions":[["b6b7"]],"note":"Use the king to take away the escape squares."
  },
  {
    "id":"back-rank","level":"easy","title":"Back-rank curtain","source":"Curated mating pattern","fen":"7k/5Q2/7K/8/8/8/8/8 w - - 0 1","solutions":[["f7e8"],["f7f8"],["f7g7"],["f7h7"]],"note":"Several queen moves mate; the board accepts each of them."
  },
  {
    "id":"deflect-the-rook","level":"medium","title":"Deflect the rook","source":"Lichess puzzle o9qyK · rating 1368","fen":"r2r2k1/1Qp1qppp/p7/8/8/P6P/1PP2PP1/2KR1B1R b - - 0 1","solutions":[["e7g5","c1b1","d8d1"]],"note":"The king is exposed, but the decisive idea begins with deflection rather than a grab."
  },
  {
    "id":"clear-the-file","level":"medium","title":"Clear the file","source":"Curated forcing line","fen":"5rk1/6pp/8/8/3Q4/8/8/5RK1 w - - 0 1","solutions":[["d4d8","f8d8","f1f8"]],"note":"Offer the queen to clear the f-file, then use the rook with tempo."
  },
  {
    "id":"knight-sacrifice","level":"medium","title":"Knight sacrifice","source":"Curated opening tactic","fen":"r1bqkb1r/pppp1ppp/2n5/3np1N1/2B1P3/8/PPPP1PPP/RNBQK2R w KQkq - 0 7","solutions":[["g5f7","e8f7","d1f3"]],"note":"The first move is a sacrifice; calculate the king chase before committing."
  },
  {
    "id":"legal-attack","level":"hard","title":"The Légal attack","source":"Curated classical attacking line","fen":"rnbqk1nr/ppp2p1p/3p2p1/4p3/2B1P1b1/2N2N2/PPPP1PPP/R1BQK2R w KQkq - 0 5","solutions":[["f3e5","g4d1","c4f7","e8e7","c3d5"]],"note":"Calculate through the queen sacrifice: the minor pieces take over the attack."
  },
  {
    "id":"defuse-the-attack","level":"hard","title":"Defuse the attack","source":"Curated classical defensive line","fen":"r1bqkb1r/pppp1Npp/2n5/3np3/2B1P3/8/PPPP1PPP/RNBQK2R b KQkq - 0 7","solutions":[["e8f7","d1f3","f7e6","b1c3","c6d4"]],"note":"The knight sacrifice looks alarming. Calculate the king route and the active counterplay, not merely the first check."
  },
  {
    "id":"pawn-endgame-zugzwang","level":"hard","title":"Pawn-endgame zugzwang","source":"Lichess puzzle XGn5Q · rating 1939","fen":"8/8/p1p4p/1pP2kp1/1P6/P4P1P/5K2/8 b - - 1 1","solutions":[["f5f4","f2g2","h6h5","g2f2","h5h4","f2e2","f4g3"]],"note":"No checks, no loose queens: calculate the pawn race until the breakthrough is certain."
  }
]
